NetkillerBlockchainFix1/README.md
NetkillerBlockchainFix1/__init__.py
NetkillerBlockchainFix1/__main__.py
NetkillerBlockchainFix1/file.epub
NetkillerBlockchainFix1/index.html
NetkillerBlockchainFix1/css/__init__.py
NetkillerBlockchainFix1/css/annotations.css
NetkillerBlockchainFix1/css/main.css
NetkillerBlockchainFix1/css/normalize.css
NetkillerBlockchainFix1/css/popup.css
NetkillerBlockchainFix1/font/__init__.py
NetkillerBlockchainFix1/font/fontello.eot
NetkillerBlockchainFix1/font/fontello.svg
NetkillerBlockchainFix1/font/fontello.ttf
NetkillerBlockchainFix1/font/fontello.woff
NetkillerBlockchainFix1/img/__init__.py
NetkillerBlockchainFix1/img/annotator-glyph-sprite.png
NetkillerBlockchainFix1/img/annotator-icon-sprite.png
NetkillerBlockchainFix1/img/apple-touch-icon.png
NetkillerBlockchainFix1/img/cancelfullscreen.png
NetkillerBlockchainFix1/img/close.png
NetkillerBlockchainFix1/img/fullscreen.png
NetkillerBlockchainFix1/img/loader.gif
NetkillerBlockchainFix1/img/menu-icon.png
NetkillerBlockchainFix1/img/save.png
NetkillerBlockchainFix1/img/saved.png
NetkillerBlockchainFix1/img/settings-s.png
NetkillerBlockchainFix1/img/settings.png
NetkillerBlockchainFix1/img/star.png
NetkillerBlockchainFix1/js/__init__.py
NetkillerBlockchainFix1/js/epub.js
NetkillerBlockchainFix1/js/epub.min.js
NetkillerBlockchainFix1/js/epub.min.map
NetkillerBlockchainFix1/js/hooks.min.js
NetkillerBlockchainFix1/js/hooks.min.map
NetkillerBlockchainFix1/js/reader.js
NetkillerBlockchainFix1/js/reader.js.map
NetkillerBlockchainFix1/js/reader.min.js
NetkillerBlockchainFix1/js/reader.min.map
NetkillerBlockchainFix1/js/hooks/__init__.py
NetkillerBlockchainFix1/js/hooks/extensions/__init__.py
NetkillerBlockchainFix1/js/hooks/extensions/highlight.js
NetkillerBlockchainFix1/js/libs/__init__.py
NetkillerBlockchainFix1/js/libs/jquery.min.js
NetkillerBlockchainFix1/js/libs/localforage.min.js
NetkillerBlockchainFix1/js/libs/screenfull.js
NetkillerBlockchainFix1/js/libs/screenfull.min.js
netkiller_blockchain_fix1-2025.3.24.1.dist-info/METADATA
netkiller_blockchain_fix1-2025.3.24.1.dist-info/WHEEL
netkiller_blockchain_fix1-2025.3.24.1.dist-info/entry_points.txt
netkiller_blockchain_fix1-2025.3.24.1.dist-info/top_level.txt
netkiller_blockchain_fix1-2025.3.24.1.dist-info/RECORD
